{
"type": "FeatureCollection",
"name": "Columbus Circle",
"crs": { "type": "name", "properties": { "name": "urn:ogc:def:crs:OGC:1.3:CRS84" } },
"features": [
{ "type": "Feature", "properties": { "id": null }, "geometry": { "type": "Point", "coordinates": [ -73.981721559592188, 40.768380423600732 ] } }
]
}
